tableschema_bigquery/VERSION
tableschema_bigquery/__init__.py
tableschema_bigquery/mapper.py
tableschema_bigquery/storage.py
tableschema_bigquery-1.0.1.dist-info/LICENSE.md
tableschema_bigquery-1.0.1.dist-info/METADATA
tableschema_bigquery-1.0.1.dist-info/WHEEL
tableschema_bigquery-1.0.1.dist-info/top_level.txt
tableschema_bigquery-1.0.1.dist-info/RECORD
