Metadata-Version: 2.1
Name: tableschema-bigquery
Version: 1.0.1
Summary: Generate BigQuery tables, load and extract data, based on JSON Table Schema descriptors.
Home-page: https://github.com/frictionlessdata/jsontableschema-bigquery-py
Author: Open Knowledge Foundation
Author-email: info@okfn.org
License: MIT
Keywords: frictionless data
Platform: UNKNOWN
Classifier: Development Status :: 4 - Beta
Classifier: Environment :: Web Environment
Classifier: Intended Audience :: Developers
Classifier: License :: OSI Approved :: MIT License
Classifier: Operating System :: OS Independent
Classifier: Programming Language :: Python :: 2
Classifier: Programming Language :: Python :: 2.7
Classifier: Programming Language :: Python :: 3
Classifier: Programming Language :: Python :: 3.3
Classifier: Programming Language :: Python :: 3.4
Classifier: Programming Language :: Python :: 3.5
Classifier: Topic :: Internet :: WWW/HTTP :: Dynamic Content
Classifier: Topic :: Software Development :: Libraries :: Python Modules
Requires-Dist: six (>=1.9)
Requires-Dist: rsa (<=4.0)
Requires-Dist: python-slugify (>=1.2)
Requires-Dist: google-api-python-client (>=1.5)
Requires-Dist: unicodecsv (>=0.14)
Requires-Dist: tableschema (>=1.0)
Requires-Dist: tabulator (>=1.0)
Provides-Extra: develop
Requires-Dist: mock ; extra == 'develop'
Requires-Dist: pylama ; extra == 'develop'
Requires-Dist: pytest ; extra == 'develop'
Requires-Dist: pytest-cov ; extra == 'develop'
Requires-Dist: oauth2client ; extra == 'develop'
Requires-Dist: tox ; extra == 'develop'
